README.txt
setup.cfg
setup.py
hebill_websites_core/__constants__.py
hebill_websites_core/__init__.py
hebill_websites_core.egg-info/PKG-INFO
hebill_websites_core.egg-info/SOURCES.txt
hebill_websites_core.egg-info/dependency_links.txt
hebill_websites_core.egg-info/top_level.txt
hebill_websites_core/websites_core/__init__.py
hebill_websites_core/websites_core/__settings__.py
hebill_websites_core/websites_core/website_core/__init__.py